src/bcd_mux.vhd
----------------------------------------------------------------------------------
-- Company: 
-- Engineer: 
-- 
-- Create Date: 04/04/2025 12:44:00 AM
-- Design Name: 
-- Module Name: bcd_mux - Behavioral
-- Project Name: 
-- Target Devices: 
-- Tool Versions: 
-- Description: 
-- 
-- Dependencies: 
-- 
-- Revision:
-- Revision 0.01 - File Created
-- Additional Comments:
-- 
----------------------------------------------------------------------------------


library IEEE;
use IEEE.STD_LOGIC_1164.ALL;

-- Uncomment the following library declaration if using
-- arithmetic functions with Signed or Unsigned values
--use IEEE.NUMERIC_STD.ALL;

-- Uncomment the following library declaration if instantiating
-- any Xilinx leaf cells in this code.
--library UNISIM;
--use UNISIM.VComponents.all;

entity bcd_mux is
    --Generic (
    --    N_DIGITS : integer := 3;
    --    N_SIGNALS : integer := 2;
    --    N_DISPLAYS : integer := 8
    --);
    Port ( clk : in STD_LOGIC;
           hold : in STD_LOGIC;
           bcd : in STD_LOGIC_VECTOR (23 downto 0);--((N_DIGITS*4)*N_SIGNALS)-1
           bin : out STD_LOGIC_VECTOR (3 downto 0);
           anodes : out STD_LOGIC_VECTOR (7 downto 0);--N_DISPLAYS-1
           range_error : out STD_LOGIC);
end bcd_mux;

architecture Behavioral of bcd_mux is
    signal sig_bcd : STD_LOGIC_VECTOR (23 downto 0); --(N_DIGITS*4-1)*N_SIGNALS
    signal sig_anodes : STD_LOGIC_VECTOR (7 downto 0); -- choice subtype is not locally staticTerosHDL
begin

    -- Main multiplexer process
    multiplex : process (clk) is
    begin
    
      if rising_edge(clk) then
        --todo if in range range_error <= '1'; move to bin2bcd?

        -- Hold the value if hold is active
        if hold = '0' then
            sig_bcd <= bcd;
        end if;
    
            -- Multiplex according to previous anode position
            case sig_anodes is --todo unhardcode
                when b"1011_1111" =>
                    sig_anodes <= b"1111_1110";
                    bin <= sig_bcd(3 downto 0);
                when b"1111_1110" =>
                    sig_anodes <= b"1111_1101";
                    bin <= sig_bcd(7 downto 4);
                when b"1111_1101" =>
                    sig_anodes <= b"1111_1011";
                    bin <= sig_bcd(11 downto 8);
                when b"1111_1011" =>
                    sig_anodes <= b"1110_1111";
                    bin <= sig_bcd(15 downto 12);
                when b"1110_1111" =>
                    sig_anodes <= b"1101_1111";
                    bin <= sig_bcd(19 downto 16);
                when b"1101_1111" =>
                    sig_anodes <= b"1011_1111";
                    bin <= sig_bcd(23 downto 20);
                when others => --for initialization
                    sig_anodes <= b"1011_1111";
            end case;

      end if;    
    end process multiplex;

    anodes <= sig_anodes;
end Behavioral;

src/tb/tb_bcd_mux.vhd
-- Testbench automatically generated online
-- at https://vhdl.lapinoo.net
-- Generation date : Fri, 04 Apr 2025 11:35:20 GMT
-- Request id : cfwk-fed377c2-67efc3f8d9823

library ieee;
use ieee.std_logic_1164.all;
use ieee.numeric_std.all;

entity tb_bcd_mux is
end tb_bcd_mux;

architecture tb of tb_bcd_mux is

    component bcd_mux
        --generic (
        --    N_DIGITS : integer := 3;
        --    N_SIGNALS : integer := 2;
        --    N_DISPLAYS : integer := 8
        --);
        port (clk         : in std_logic;
              hold        : in std_logic;
              bcd         : in std_logic_vector (23 downto 0); --N_DIGITS*4*N_SIGNALS-1
              bin         : out std_logic_vector (3 downto 0);
              anodes      : out std_logic_vector (7 downto 0); --N_DISPLAYS-1
              range_error : out std_logic);
    end component;

    signal clk         : std_logic;
    signal hold        : std_logic;
    constant C_NDIGITS : integer := 3;
    constant C_NSIGNALS : integer := 2;
    signal bcd         : std_logic_vector (C_NDIGITS*4*C_NSIGNALS-1 downto 0);
    signal bin         : std_logic_vector (3 downto 0);
    constant C_NDISPLAYS : integer := 8;
    signal anodes      : std_logic_vector (C_NDISPLAYS-1 downto 0);
    signal range_error : std_logic;

    constant TbPeriod : time := 10 ns; -- ***EDIT*** Put right period here
    signal TbClock : std_logic := '0';
    signal TbSimEnded : std_logic := '0';

begin

    dut : bcd_mux
    --generic map (
    --    N_DIGITS => C_NDIGITS,
    --    N_SIGNALS => C_NSIGNALS,
    --    N_DISPLAYS => C_NDISPLAYS
    --)
    port map (clk         => clk,
              hold        => hold,
              bcd         => bcd,
              bin         => bin,
              anodes      => anodes,
              range_error => range_error);

    -- Clock generation
    TbClock <= not TbClock after TbPeriod/2 when TbSimEnded /= '1' else '0';

    -- ***EDIT*** Check that clk is really your main clock signal
    clk <= TbClock;

    stimuli : process
    begin
        -- ***EDIT*** Adapt initialization as needed
        hold <= '0';

        bcd <= b"1000_1001_1010_1100_1101_1110";
        --bcd <= x"8"&x"9"&x"a"&x"c"&x"d"&x"e";
        wait for 6 * TbPeriod;

        bcd <= x"a"&x"4"&x"0"&x"4"&x"5"&x"9";
        wait for 6 * TbPeriod;

        hold <= '1';
        wait for 2 * TbPeriod;

        bcd <= x"c"&x"b"&x"a"&x"d"&x"f"&x"f";
        wait for 6 * TbPeriod;

        hold <= '0';
        wait for 2 * TbPeriod;

        bcd <= x"9"&x"8"&x"7"&x"6"&x"5"&x"4";
        wait for 6 * TbPeriod;

        -- ***EDIT*** Add stimuli here
        --wait for 100 * TbPeriod;

        -- Stop the clock and hence terminate the simulation
        TbSimEnded <= '1';
        wait;
    end process;

end tb;

-- Configuration block below is required by some simulators. Usually no need to edit.

configuration cfg_tb_bcd_mux of tb_bcd_mux is
    for tb
    end for;
end cfg_tb_bcd_mux;

img/tb_bcd_mux.vcd
$date
  Fri Apr  4 15:22:13 2025
$end
$version
  GHDL v0
$end
$timescale
  1 fs
$end
$scope module standard $end
$upscope $end
$scope module textio $end
$upscope $end
$scope module std_logic_1164 $end
$upscope $end
$scope module numeric_std $end
$upscope $end
$scope module tb_bcd_mux $end
$var reg 1 ! clk $end
$var reg 1 " hold $end
$var reg 24 # bcd[23:0] $end
$var reg 4 $ bin[3:0] $end
$var reg 8 % anodes[7:0] $end
$var reg 1 & range_error $end
$var reg 1 ' tbclock $end
$var reg 1 ( tbsimended $end
$scope module dut $end
$var reg 1 ) clk $end
$var reg 1 * hold $end
$var reg 24 + bcd[23:0] $end
$var reg 4 , bin[3:0] $end
$var reg 8 - anodes[7:0] $end
$var reg 1 . range_error $end
$var reg 24 / sig_bcd[23:0] $end
$var reg 8 0 sig_anodes[7:0] $end
$upscope $end
$upscope $end
$enddefinitions $end
#0
0!
0"
b100010011010110011011110 #
bUUUU $
bUUUUUUUU %
U&
0'
0(
0)
0*
b100010011010110011011110 +
bUUUU ,
bUUUUUUUU -
U.
bUUUUUUUUUUUUUUUUUUUUUUUU /
bUUUUUUUU 0
#5000000
1!
b10111111 %
1'
1)
b10111111 -
b100010011010110011011110 /
b10111111 0
#10000000
0!
0'
0)
#15000000
1!
b1110 $
b11111110 %
1'
1)
b1110 ,
b11111110 -
b11111110 0
#20000000
0!
0'
0)
#25000000
1!
b1101 $
b11111101 %
1'
1)
b1101 ,
b11111101 -
b11111101 0
#30000000
0!
0'
0)
#35000000
1!
b1100 $
b11111011 %
1'
1)
b1100 ,
b11111011 -
b11111011 0
#40000000
0!
0'
0)
#45000000
1!
b1010 $
b11101111 %
1'
1)
b1010 ,
b11101111 -
b11101111 0
#50000000
0!
0'
0)
#55000000
1!
b1001 $
b11011111 %
1'
1)
b1001 ,
b11011111 -
b11011111 0
#60000000
0!
b101001000000010001011001 #
0'
0)
b101001000000010001011001 +
#65000000
1!
b1000 $
b10111111 %
1'
1)
b1000 ,
b10111111 -
b101001000000010001011001 /
b10111111 0
#70000000
0!
0'
0)
#75000000
1!
b1001 $
b11111110 %
1'
1)
b1001 ,
b11111110 -
b11111110 0
#80000000
0!
0'
0)
#85000000
1!
b0101 $
b11111101 %
1'
1)
b0101 ,
b11111101 -
b11111101 0
#90000000
0!
0'
0)
#95000000
1!
b0100 $
b11111011 %
1'
1)
b0100 ,
b11111011 -
b11111011 0
#100000000
0!
0'
0)
#105000000
1!
b0000 $
b11101111 %
1'
1)
b0000 ,
b11101111 -
b11101111 0
#110000000
0!
0'
0)
#115000000
1!
b0100 $
b11011111 %
1'
1)
b0100 ,
b11011111 -
b11011111 0
#120000000
0!
1"
0'
0)
1*
#125000000
1!
b1010 $
b10111111 %
1'
1)
b1010 ,
b10111111 -
b10111111 0
#130000000
0!
0'
0)
#135000000
1!
b1001 $
b11111110 %
1'
1)
b1001 ,
b11111110 -
b11111110 0
#140000000
0!
b110010111010110111111111 #
0'
0)
b110010111010110111111111 +
#145000000
1!
b0101 $
b11111101 %
1'
1)
b0101 ,
b11111101 -
b11111101 0
#150000000
0!
0'
0)
#155000000
1!
b0100 $
b11111011 %
1'
1)
b0100 ,
b11111011 -
b11111011 0
#160000000
0!
0'
0)
#165000000
1!
b0000 $
b11101111 %
1'
1)
b0000 ,
b11101111 -
b11101111 0
#170000000
0!
0'
0)
#175000000
1!
b0100 $
b11011111 %
1'
1)
b0100 ,
b11011111 -
b11011111 0
#180000000
0!
0'
0)
#185000000
1!
b1010 $
b10111111 %
1'
1)
b1010 ,
b10111111 -
b10111111 0
#190000000
0!
0'
0)
#195000000
1!
b1001 $
b11111110 %
1'
1)
b1001 ,
b11111110 -
b11111110 0
#200000000
0!
0"
0'
0)
0*
#205000000
1!
b0101 $
b11111101 %
1'
1)
b0101 ,
b11111101 -
b110010111010110111111111 /
b11111101 0
#210000000
0!
0'
0)
#215000000
1!
b1101 $
b11111011 %
1'
1)
b1101 ,
b11111011 -
b11111011 0
#220000000
0!
b100110000111011001010100 #
0'
0)
b100110000111011001010100 +
#225000000
1!
b1010 $
b11101111 %
1'
1)
b1010 ,
b11101111 -
b100110000111011001010100 /
b11101111 0
#230000000
0!
0'
0)
#235000000
1!
b1000 $
b11011111 %
1'
1)
b1000 ,
b11011111 -
b11011111 0
#240000000
0!
0'
0)
#245000000
1!
b1001 $
b10111111 %
1'
1)
b1001 ,
b10111111 -
b10111111 0
#250000000
0!
0'
0)
#255000000
1!
b0100 $
b11111110 %
1'
1)
b0100 ,
b11111110 -
b11111110 0
#260000000
0!
0'
0)
#265000000
1!
b0101 $
b11111101 %
1'
1)
b0101 ,
b11111101 -
b11111101 0
#270000000
0!
0'
0)
#275000000
1!
b0110 $
b11111011 %
1'
1)
b0110 ,
b11111011 -
b11111011 0
#280000000
0!
0'
1(
0)
