src/bcd_mux.vhd
----------------------------------------------------------------------------------
-- Company: 
-- Engineer: 
-- 
-- Create Date: 04/04/2025 12:44:00 AM
-- Design Name: 
-- Module Name: bcd_mux - Behavioral
-- Project Name: 
-- Target Devices: 
-- Tool Versions: 
-- Description: 
-- 
-- Dependencies: 
-- 
-- Revision:
-- Revision 0.01 - File Created
-- Additional Comments:
-- 
----------------------------------------------------------------------------------


library IEEE;
use IEEE.STD_LOGIC_1164.ALL;

-- Uncomment the following library declaration if using
-- arithmetic functions with Signed or Unsigned values
--use IEEE.NUMERIC_STD.ALL;

-- Uncomment the following library declaration if instantiating
-- any Xilinx leaf cells in this code.
--library UNISIM;
--use UNISIM.VComponents.all;

-- Entity displays maximum of two hex numbers one to four digits wide
-- Should be instantiated

entity bcd_mux is
    Generic (
        N_DIGITS : integer range 1 to 4 := 3;                             -- Digits used for single number
        N_SIGNALS : integer range 1 to 2 := 2                            -- Numbers displayed
    );
    Port ( clk      : in STD_LOGIC;                          -- Component clock, controls the multiplexer speed (ideally 50 ms)
           hold     : in STD_LOGIC;                          -- Hold the current displayed values
           bcd      : in STD_LOGIC_VECTOR ((N_DIGITS*4)*N_SIGNALS-1 downto 0);  -- BCD inputs for all digits
           bin      : out STD_LOGIC_VECTOR (3 downto 0);     -- Binary output to 7 segment display component
           anodes   : out STD_LOGIC_VECTOR (7 downto 0));     -- 7 segment display anode vector, supports 8 displays
end bcd_mux;

architecture Behavioral of bcd_mux is
    signal sig_bcd : STD_LOGIC_VECTOR ((N_DIGITS*4)*N_SIGNALS-1 downto 0); -- BCD signal buffer
    signal next_digit : integer range 0 to N_DIGITS*N_SIGNALS-1 := 0;                -- Next digit to display
    signal space : integer range 1 to 3 := 4 - N_DIGITS; -- make constant out of this
begin

    -- Main multiplexer process
    -- Triggers on every clock input
    multiplex : process (clk) is
    begin

      if rising_edge(clk) then
        -- Hold the value if hold is active,
        -- buffer new input value if hold inactive.
        if hold = '0' then
            sig_bcd <= bcd;
        end if;

            -- Multiplex according to next digit number
            -- 1. separate one digit from the buffer
            -- 2. activate corresponding display anode and space it if two signals
            -- 3. write the next digit or start ahead

            bin <= sig_bcd(next_digit*4+3 downto next_digit*4);

            anodes <= (others => '1');
            if N_SIGNALS = 2 and next_digit >= N_DIGITS then
                anodes(next_digit+space) <= '0';
            else
                anodes(next_digit) <= '0';
            end if;

            if next_digit < N_DIGITS*N_SIGNALS-1 then
                next_digit <= next_digit + 1;
            else
                next_digit <= 0;
            end if;

      end if;    
    end process multiplex;

end Behavioral;

src/tb/tb_bcd_mux.vhd
-- Testbench automatically generated online
-- at https://vhdl.lapinoo.net
-- Generation date : Fri, 04 Apr 2025 11:35:20 GMT
-- Request id : cfwk-fed377c2-67efc3f8d9823

library ieee;
use ieee.std_logic_1164.all;
use ieee.numeric_std.all;

entity tb_bcd_mux is
end tb_bcd_mux;

architecture tb of tb_bcd_mux is

    component bcd_mux
        --generic (
        --    N_DIGITS : integer := 3;
        --    N_SIGNALS : integer := 2;
        --    N_DISPLAYS : integer := 8
        --);
        port (clk         : in std_logic;
              hold        : in std_logic;
              bcd         : in std_logic_vector (23 downto 0); --N_DIGITS*4*N_SIGNALS-1
              bin         : out std_logic_vector (3 downto 0);
              anodes      : out std_logic_vector (7 downto 0)); --N_DISPLAYS-1
    end component;

    signal clk         : std_logic;
    signal hold        : std_logic;
    constant C_NDIGITS : integer := 3;
    constant C_NSIGNALS : integer := 2;
    signal bcd         : std_logic_vector (C_NDIGITS*4*C_NSIGNALS-1 downto 0);
    signal bin         : std_logic_vector (3 downto 0);
    constant C_NDISPLAYS : integer := 8;
    signal anodes      : std_logic_vector (C_NDISPLAYS-1 downto 0);

    constant TbPeriod : time := 10 ns; -- ***EDIT*** Put right period here
    signal TbClock : std_logic := '0';
    signal TbSimEnded : std_logic := '0';

begin

    dut : bcd_mux
    --generic map (
    --    N_DIGITS => C_NDIGITS,
    --    N_SIGNALS => C_NSIGNALS,
    --    N_DISPLAYS => C_NDISPLAYS
    --)
    port map (clk         => clk,
              hold        => hold,
              bcd         => bcd,
              bin         => bin,
              anodes      => anodes);

    -- Clock generation
    TbClock <= not TbClock after TbPeriod/2 when TbSimEnded /= '1' else '0';

    -- ***EDIT*** Check that clk is really your main clock signal
    clk <= TbClock;

    stimuli : process
    begin
        -- ***EDIT*** Adapt initialization as needed
        hold <= '0';

        bcd <= b"1000_1001_1010_1100_1101_1110";
        --bcd <= x"8"&x"9"&x"a"&x"c"&x"d"&x"e";
        wait for 6 * TbPeriod;

        bcd <= x"a"&x"4"&x"0"&x"4"&x"5"&x"9";
        wait for 6 * TbPeriod;

        hold <= '1';
        wait for 2 * TbPeriod;

        bcd <= x"c"&x"b"&x"a"&x"d"&x"f"&x"f";
        wait for 6 * TbPeriod;

        hold <= '0';
        wait for 2 * TbPeriod;

        bcd <= x"9"&x"8"&x"7"&x"6"&x"5"&x"4";
        wait for 6 * TbPeriod;

        -- ***EDIT*** Add stimuli here
        --wait for 100 * TbPeriod;

        -- Stop the clock and hence terminate the simulation
        TbSimEnded <= '1';
        wait;
    end process;

end tb;

-- Configuration block below is required by some simulators. Usually no need to edit.

configuration cfg_tb_bcd_mux of tb_bcd_mux is
    for tb
    end for;
end cfg_tb_bcd_mux;

img/tb_bcd_mux.vcd
$date
  Thu Apr 17 01:02:37 2025
$end
$version
  GHDL v0
$end
$timescale
  1 fs
$end
$scope module standard $end
$upscope $end
$scope module textio $end
$upscope $end
$scope module std_logic_1164 $end
$upscope $end
$scope module numeric_std $end
$upscope $end
$scope module tb_bcd_mux $end
$var reg 1 ! clk $end
$var reg 1 " hold $end
$var reg 24 # bcd[23:0] $end
$var reg 4 $ bin[3:0] $end
$var reg 8 % anodes[7:0] $end
$var reg 1 & tbclock $end
$var reg 1 ' tbsimended $end
$scope module dut $end
$var reg 1 ( clk $end
$var reg 1 ) hold $end
$var reg 24 * bcd[23:0] $end
$var reg 4 + bin[3:0] $end
$var reg 8 , anodes[7:0] $end
$var reg 24 - sig_bcd[23:0] $end
$var integer 32 . next_digit $end
$upscope $end
$upscope $end
$enddefinitions $end
#0
0!
0"
b100010011010110011011110 #
bUUUU $
bUUUUUUUU %
0&
0'
0(
0)
b100010011010110011011110 *
bUUUU +
bUUUUUUUU ,
bUUUUUUUUUUUUUUUUUUUUUUUU -
b0 .
#5000000
1!
b11111110 %
1&
1(
b11111110 ,
b100010011010110011011110 -
b1 .
#10000000
0!
0&
0(
#15000000
1!
b1101 $
b11111101 %
1&
1(
b1101 +
b11111101 ,
b10 .
#20000000
0!
0&
0(
#25000000
1!
b1100 $
b11111011 %
1&
1(
b1100 +
b11111011 ,
b11 .
#30000000
0!
0&
0(
#35000000
1!
b1010 $
b11101111 %
1&
1(
b1010 +
b11101111 ,
b100 .
#40000000
0!
0&
0(
#45000000
1!
b1001 $
b11011111 %
1&
1(
b1001 +
b11011111 ,
b101 .
#50000000
0!
0&
0(
#55000000
1!
b1000 $
b10111111 %
1&
1(
b1000 +
b10111111 ,
b0 .
#60000000
0!
b101001000000010001011001 #
0&
0(
b101001000000010001011001 *
#65000000
1!
b1110 $
b11111110 %
1&
1(
b1110 +
b11111110 ,
b101001000000010001011001 -
b1 .
#70000000
0!
0&
0(
#75000000
1!
b0101 $
b11111101 %
1&
1(
b0101 +
b11111101 ,
b10 .
#80000000
0!
0&
0(
#85000000
1!
b0100 $
b11111011 %
1&
1(
b0100 +
b11111011 ,
b11 .
#90000000
0!
0&
0(
#95000000
1!
b0000 $
b11101111 %
1&
1(
b0000 +
b11101111 ,
b100 .
#100000000
0!
0&
0(
#105000000
1!
b0100 $
b11011111 %
1&
1(
b0100 +
b11011111 ,
b101 .
#110000000
0!
0&
0(
#115000000
1!
b1010 $
b10111111 %
1&
1(
b1010 +
b10111111 ,
b0 .
#120000000
0!
1"
0&
0(
1)
#125000000
1!
b1001 $
b11111110 %
1&
1(
b1001 +
b11111110 ,
b1 .
#130000000
0!
0&
0(
#135000000
1!
b0101 $
b11111101 %
1&
1(
b0101 +
b11111101 ,
b10 .
#140000000
0!
b110010111010110111111111 #
0&
0(
b110010111010110111111111 *
#145000000
1!
b0100 $
b11111011 %
1&
1(
b0100 +
b11111011 ,
b11 .
#150000000
0!
0&
0(
#155000000
1!
b0000 $
b11101111 %
1&
1(
b0000 +
b11101111 ,
b100 .
#160000000
0!
0&
0(
#165000000
1!
b0100 $
b11011111 %
1&
1(
b0100 +
b11011111 ,
b101 .
#170000000
0!
0&
0(
#175000000
1!
b1010 $
b10111111 %
1&
1(
b1010 +
b10111111 ,
b0 .
#180000000
0!
0&
0(
#185000000
1!
b1001 $
b11111110 %
1&
1(
b1001 +
b11111110 ,
b1 .
#190000000
0!
0&
0(
#195000000
1!
b0101 $
b11111101 %
1&
1(
b0101 +
b11111101 ,
b10 .
#200000000
0!
0"
0&
0(
0)
#205000000
1!
b0100 $
b11111011 %
1&
1(
b0100 +
b11111011 ,
b110010111010110111111111 -
b11 .
#210000000
0!
0&
0(
#215000000
1!
b1010 $
b11101111 %
1&
1(
b1010 +
b11101111 ,
b100 .
#220000000
0!
b100110000111011001010100 #
0&
0(
b100110000111011001010100 *
#225000000
1!
b1011 $
b11011111 %
1&
1(
b1011 +
b11011111 ,
b100110000111011001010100 -
b101 .
#230000000
0!
0&
0(
#235000000
1!
b1001 $
b10111111 %
1&
1(
b1001 +
b10111111 ,
b0 .
#240000000
0!
0&
0(
#245000000
1!
b0100 $
b11111110 %
1&
1(
b0100 +
b11111110 ,
b1 .
#250000000
0!
0&
0(
#255000000
1!
b0101 $
b11111101 %
1&
1(
b0101 +
b11111101 ,
b10 .
#260000000
0!
0&
0(
#265000000
1!
b0110 $
b11111011 %
1&
1(
b0110 +
b11111011 ,
b11 .
#270000000
0!
0&
0(
#275000000
1!
b0111 $
b11101111 %
1&
1(
b0111 +
b11101111 ,
b100 .
#280000000
0!
0&
1'
0(
